{"pageProps":{"article":{"id":3,"title":"Cara Perawatan Besi Bangunan agar Tidak Mudah Berkarat","slug":"cara-perawatan-besi-bangunan-anti-karat","excerpt":"Panduan praktis merawat material besi pada konstruksi bangunan agar tahan lama dan tidak mudah berkarat.","content":"\n      <h2>Pentingnya Perawatan Besi pada Konstruksi</h2>\n      <p>Besi merupakan material utama dalam konstruksi bangunan yang memerlukan perawatan khusus...</p>\n      \n      <h3>Langkah-langkah Perawatan</h3>\n      <ol>\n        <li>Pembersihan rutin dari kotoran dan debu</li>\n        <li>Aplikasi cat anti karat secara berkala</li>\n        <li>Kontrol kelembaban lingkungan sekitar</li>\n      </ol>\n    ","image":"/images/articles/perawatan-besi.jpg","author":"Tim Mitra Bangun Indo Baja","publishedAt":"2025-01-10","category":"Maintenance","tags":["besi","perawatan","anti karat"],"readTime":6}},"__N_SSG":true}